dicthandling.py
dicthandling-0.2b2.dist-info/LICENSE
dicthandling-0.2b2.dist-info/METADATA
dicthandling-0.2b2.dist-info/WHEEL
dicthandling-0.2b2.dist-info/top_level.txt
dicthandling-0.2b2.dist-info/RECORD
