Metadata-Version: 2.1
Name: dicthandling
Version: 0.2b2
Summary: Frequently used methods used for handling nested dictionaries.
Home-page: https://gitlab.com/david.scheliga/dicthandling
Author: David Scheliga
Author-email: david.scheliga@gmx.de
License: GNU General Public License v3 (GPLv3)
Keywords: dictionary,nested,handling
Platform: UNKNOWN
Classifier: Development Status :: 4 - Beta
Classifier: License :: OSI Approved :: GNU General Public License v3 (GPLv3)
Classifier: Operating System :: OS Independent
Classifier: Programming Language :: Python :: 3
Requires-Python: >=3.6
